pyfinch/__init__.py
pyfinch-0.0.1.dist-info/LICENSE
pyfinch-0.0.1.dist-info/METADATA
pyfinch-0.0.1.dist-info/WHEEL
pyfinch-0.0.1.dist-info/top_level.txt
pyfinch-0.0.1.dist-info/RECORD
