Metadata-Version: 2.1
Name: pyfinch
Version: 0.0.1
Summary: A python package for analyzing neural & bioacoustics signals from songbirds
Home-page: https://github.com/JaerongA/pyfinch
Author: Jaerong Ahn
Author-email: jaerongahn@gmail.com
License: BSD 3-Clause License
Keywords: python,songbird,zebra finch,neuroscience,bioacoustics
Platform: UNKNOWN
Classifier: Development Status :: 3 - Alpha
Classifier: Intended Audience :: Science/Research
Classifier: Programming Language :: Python :: 3
Classifier: License :: OSI Approved :: BSD License
Classifier: Operating System :: OS Independent
Requires-Python: >=3.7
License-File: LICENSE
Requires-Dist: librosa (==0.9.0)
Requires-Dist: matplotlib (==3.3.4)
Requires-Dist: numpy (==1.20.1)
Requires-Dist: pandas (==1.2.4)
Requires-Dist: scikit-learn (==1.0.2)
Requires-Dist: scikit-posthocs (==0.6.7)
Requires-Dist: scipy (==1.6.2)
Requires-Dist: seaborn (==0.11.2)
Requires-Dist: soundfile (==0.10.3.post1)
Requires-Dist: statsmodels (==0.13.0)
